{"name":"动漫","slug":"动漫","count":1,"postlist":[{"title":"少年锦衣卫","uid":"66f8f7d27f8f11373e4fb735c4ddd2f3","slug":"少年锦衣卫","date":"2024-03-21T14:17:41.000Z","updated":"2024-03-21T14:38:49.034Z","comments":true,"path":"api/articles/少年锦衣卫.json","keywords":null,"cover":"https://raw.githubusercontent.com/3309446352/Images/main/img/少年锦衣卫.jpg","text":"少年锦衣卫 似水流年▪落英 晚夜微雨问海棠-镜予歌 / 陈亦洺 / 喧笑","permalink":"/post/少年锦衣卫","photos":[],"count_time":{"symbolsCount":47,"symbolsTime":"1 mins."},"categories":[{"name":"动漫","slug":"动漫","count":1,"path":"api/categories/动漫.json"}],"tags":[{"name":"动漫","slug":"动漫","count":1,"path":"api/tags/动漫.json"},{"name":"音乐","slug":"音乐","count":1,"path":"api/tags/音乐.json"}],"author":{"name":"ZMC","slug":"zmc","avatar":"https://raw.githubusercontent.com/3309446352/Images/main/img/illust_77229305_20210626_204628.png","link":"https://tridiamond.tech","description":"Think like an artist, code like an artisan.","socials":{"github":"https://github.com/tridiamond","twitter":"","stackoverflow":"","wechat":"","qq":"","weibo":"","zhihu":"","csdn":"","juejin":"","customs":{}}}}]}